rosecape_airflow/__init__.py
rosecape_airflow/aws/__init__.py
rosecape_airflow/aws/ec2.py
rosecape_airflow/aws/ecs.py
rosecape_airflow/aws/efs.py
rosecape_airflow/slack/__init__.py
rosecape_airflow/slack/messages.py
rosecape_airflow/slack/task_failed_slack_alert.py
rosecape_airflow-0.0.19.dist-info/METADATA
rosecape_airflow-0.0.19.dist-info/WHEEL
rosecape_airflow-0.0.19.dist-info/top_level.txt
rosecape_airflow-0.0.19.dist-info/RECORD
